amulet/level/__init__.py
amulet/level/__init__.pyi
amulet/level/_amulet_level.cpython-311-darwin.so
amulet/level/_amulet_level.pyi
amulet/level/_version.py
amulet/level/amulet_levelConfig.cmake
amulet/level/dll.hpp
amulet/level/libamulet_level.dylib
amulet/level/loader.hpp
amulet/level/loader.pyi
amulet/level/py.typed
amulet/level/__pyinstaller/__init__.py
amulet/level/__pyinstaller/hook-amulet.level.py
amulet/level/abc/__init__.pyi
amulet/level/abc/chunk_handle.hpp
amulet/level/abc/chunk_handle.pyi
amulet/level/abc/chunk_handle_helper.hpp
amulet/level/abc/chunk_handle_helper_impl.hpp
amulet/level/abc/dimension.hpp
amulet/level/abc/dimension.pyi
amulet/level/abc/history.hpp
amulet/level/abc/level.hpp
amulet/level/abc/level.pyi
amulet/level/abc/registry.hpp
amulet/level/abc/registry.pyi
amulet/level/bedrock/__init__.pyi
amulet/level/bedrock/chunk.hpp
amulet/level/bedrock/chunk.pyi
amulet/level/bedrock/chunk_handle.hpp
amulet/level/bedrock/chunk_handle.pyi
amulet/level/bedrock/dimension.hpp
amulet/level/bedrock/dimension.pyi
amulet/level/bedrock/level.hpp
amulet/level/bedrock/level.pyi
amulet/level/bedrock/level_dat.hpp
amulet/level/bedrock/level_dat.pyi
amulet/level/bedrock/raw_chunk.hpp
amulet/level/bedrock/raw_chunk.pyi
amulet/level/bedrock/raw_dimension.hpp
amulet/level/bedrock/raw_dimension.pyi
amulet/level/bedrock/raw_level.hpp
amulet/level/bedrock/raw_level.pyi
amulet/level/bedrock/chunk_components/__init__.pyi
amulet/level/bedrock/chunk_components/bedrock_raw_chunk_component.hpp
amulet/level/java/__init__.pyi
amulet/level/java/chunk.hpp
amulet/level/java/chunk.pyi
amulet/level/java/chunk_handle.hpp
amulet/level/java/chunk_handle.pyi
amulet/level/java/dimension.hpp
amulet/level/java/dimension.pyi
amulet/level/java/level.hpp
amulet/level/java/level.pyi
amulet/level/java/long_array.hpp
amulet/level/java/long_array.pyi
amulet/level/java/raw_dimension.hpp
amulet/level/java/raw_dimension.pyi
amulet/level/java/raw_level.hpp
amulet/level/java/raw_level.pyi
amulet_level-1.0.5a0.dist-info/METADATA
amulet_level-1.0.5a0.dist-info/WHEEL
amulet_level-1.0.5a0.dist-info/entry_points.txt
amulet_level-1.0.5a0.dist-info/top_level.txt
amulet_level-1.0.5a0.dist-info/RECORD
