Metadata-Version: 2.4
Name: amulet-level
Version: 1.0.5a0
Summary: A Python and C++ library for interacting with Minecraft worlds and structures.
Author: James Clare
Project-URL: Homepage, https://www.amuletmc.com
Project-URL: Repository, https://github.com/Amulet-Team/Amulet-Level
Project-URL: Issues, https://github.com/Amulet-Team/Amulet-Level/issues
Classifier: Programming Language :: Python :: 3
Classifier: Operating System :: OS Independent
Requires-Python: >=3.11
Requires-Dist: amulet-compiler-target==2.0
Requires-Dist: amulet-compiler-version==4.309027957683952396889703.17
Requires-Dist: pybind11==3.0.1
Requires-Dist: amulet-pybind11-extensions~=1.2.0.0a2
Requires-Dist: amulet-io~=2.0.0.0a0
Requires-Dist: amulet-leveldb~=3.0.5.0a1
Requires-Dist: amulet-utils~=1.1.3.0a8
Requires-Dist: amulet-zlib~=1.0.8.0a4
Requires-Dist: amulet-nbt~=5.0.3.0a1
Requires-Dist: amulet-core~=2.0.8.0a1
Requires-Dist: amulet-game~=1.0.4.0a0
Requires-Dist: amulet-anvil~=1.0.4.0a0
Requires-Dist: numpy~=2.0
Requires-Dist: pillow~=11.3
Provides-Extra: dev
Requires-Dist: setuptools>=42; extra == "dev"
Requires-Dist: types-setuptools; extra == "dev"
Requires-Dist: versioneer; extra == "dev"
Requires-Dist: types-versioneer; extra == "dev"
Requires-Dist: packaging; extra == "dev"
Requires-Dist: wheel; extra == "dev"
Requires-Dist: pybind11_stubgen>=2.5.4; extra == "dev"
Requires-Dist: black>=22.3; extra == "dev"
Requires-Dist: isort; extra == "dev"
Requires-Dist: autoflake; extra == "dev"
Requires-Dist: mypy; extra == "dev"
Requires-Dist: types-pyinstaller; extra == "dev"
Requires-Dist: amulet-test-utils~=1.3; extra == "dev"
Dynamic: requires-dist
